<?xml version="1.0" encoding="utf-8" ?>
<dwsync>
<file name="spacer.gif" server="C:/wamp/www/" local="128772803580000000" remote="128772803580000000" />
<file name="meetlat.gif" server="C:/wamp/www/" local="126271378100000000" remote="126271378100000000" />
<file name="BANNER.jpg" server="C:/wamp/www/" local="130414672444466182" remote="130414672440000000" />
<file name="DSCN0703.jpg" server="C:/wamp/www/" local="130431116248565304" remote="130431116240000000" />
<file name="kever.jpg" server="C:/wamp/www/" local="130441221340868873" remote="130441221340000000" />
<file name="soulage.jpg" server="C:/wamp/www/" local="130441221511533172" remote="130441221510000000" />
<file name="BRIL.jpg" server="C:/wamp/www/" local="130414753581416950" remote="130414753580000000" />
<file name="d63fec9374803d41cb864ae5b2a.jpg" server="C:/wamp/www/" local="130441242728641414" remote="130441242720000000" />
<file name="6197be2d76f67b8ce6abc90676c.jpg" server="C:/wamp/www/" local="130441264595370165" remote="130441264590000000" />
<file name="bge.jpg" server="C:/wamp/www/" local="130441357704984764" remote="130441357700000000" />
<file name="9200000027134060.jpg" server="C:/wamp/www/" local="130441428439833014" remote="130441428430000000" />
<file name="the-ones.jpg" server="C:/wamp/www/" local="130441464488012524" remote="130441464480000000" />
<file name="portrayalofDynamics2.jpg" server="C:/wamp/www/" local="130441457886704930" remote="130441457880000000" />
<file name="Brahmaea.jpg" server="C:/wamp/www/" local="130441447144485973" remote="130441447140000000" />
<file name="00005.jpg" server="C:/wamp/www/" local="126650015820000000" remote="126650015820000000" />
</dwsync>